FPGA_Verilog/debouceSM.v


module debounceSM(
	//Inputs
	signal_in, rst_n, clk,
	//Outputs
	signal_out
	);
	
	//Inputs
	input wire signal_in, rst_n, clk;
	
	//Outputs
	output reg signal_out;
	
	localparam target_count = 4'h4;
	
	localparam state_low = 2'b00;
	localparam state_posedge = 2'b01;
	localparam state_negedge = 2'b10;
	localparam state_high = 2'b11;
	
	reg [1:0] current_state, next_state;
	reg [3:0] count;
	wire [3:0] next_count;
	reg reset_count;
	
	always@(posedge clk, negedge rst_n)begin
		if(~rst_n)begin
			current_state <= 2'b00;
			count <= 4'b0000;
		end
		else begin
			current_state <= next_state;
			count <= next_count;
		end
	end
	
	assign next_count = (reset_count) ? 4'b0000 : count + 4'b0001;
	 
	always@(current_state, signal_in, count)begin
		next_state = state_low;
		signal_out = 1'b0;
		reset_count = 1'b1;
		
		case(current_state)
			
			state_low : begin
				signal_out = 1'b0;
				if(signal_in)begin
					reset_count = 1'b0;
					next_state = state_posedge;
				end
				else begin
					reset_count = 1'b1;
					next_state = state_low;
				end
			end
			
			
			state_posedge : begin
				signal_out = 1'b0;
				
				if(signal_in)begin
					reset_count = 1'b0;
				end
				else begin
					reset_count = 1'b1;
				end
				
				if(count == target_count && signal_in)begin
					next_state = state_high;
				end
				else if(signal_in)begin
					next_state = state_posedge;
				end
				else begin
					next_state = state_low;
				end
			end
			
			
			state_high : begin
				signal_out = 1'b1;
				if(~signal_in)begin
					reset_count = 1'b0;
					next_state = state_negedge;
				end
				else begin
					reset_count = 1'b1;
					next_state = state_high;
				end
			end
			

			state_negedge : begin
				signal_out = 1'b1;
				
				if(~signal_in)begin
					reset_count = 1'b0;
				end
				else begin
					reset_count = 1'b1;
				end
				
				if(count == target_count && ~signal_in)begin
					next_state = state_low;
				end
				else if(~signal_in)begin
					next_state = state_negedge;
				end
				else begin
					next_state = state_high;
				end
			end
			
			
			default : begin
				next_state = state_low;
			end
		endcase
	end

endmodule

FPGA_Verilog/DSM_tb.v
`timescale 10ns/1ns

module DSM_tb();

	reg clk, rst_n, signal_in;

	wire signal_out;

	debounceSM DUT(
		.clk(clk),
		.rst_n(rst_n),
		.signal_in(signal_in),
		.signal_out(signal_out)
		);

	initial begin
		clk = 1'b0;
		rst_n = 1'b0;
		#8
		rst_n = 1'b1;
	end

	always begin
		#5 clk = ~clk;
	end

	initial begin
		#10
		signal_in = 1'b0;
		#20
		signal_in = 1'b1;
		#10
		signal_in = 1'b0;
		#10 
		signal_in = 1'b1;
		#20
		signal_in = 1'b0;
		#10
		signal_in = 1'b1;
		#60
		
		
		#200
		$finish;
	end
	
	initial begin
		$dumpfile("tb_dump.vcd");
		$dumpvars(0,DSM_tb);
	end

endmodule

FPGA_Verilog/tb_dump.vcd
$date
	Sun May 04 11:42:59 2014
$end
$version
	Icarus Verilog
$end
$timescale
	1ns
$end
$scope module DSM_tb $end
$var wire 1 ! signal_out $end
$var reg 1 " clk $end
$var reg 1 # rst_n $end
$var reg 1 $ signal_in $end
$scope module DUT $end
$var wire 1 % clk $end
$var wire 4 & next_count [3:0] $end
$var wire 1 ' rst_n $end
$var wire 1 ( signal_in $end
$var reg 4 ) count [3:0] $end
$var reg 2 * current_state [1:0] $end
$var reg 2 + next_state [1:0] $end
$var reg 1 , reset_count $end
$var reg 1 - signal_out $end
$upscope $end
$upscope $end
$enddefinitions $end
#0
$dumpvars
0-
1,
b0 +
b0 *
b0 )
x(
0'
b0 &
0%
x$
0#
0"
0!
$end
#50
1"
1%
#80
1#
1'
#100
0"
0%
0$
0(
#150
1"
1%
#200
0"
0%
#250
1"
1%
#300
b1 &
b1 +
0,
0"
0%
1$
1(
#350
b10 &
0,
b1 +
b1 )
b1 *
1"
1%
#400
b0 &
1,
b0 +
0"
0%
0$
0(
#450
b0 )
b0 *
1"
1%
#500
b1 &
b1 +
0,
0"
0%
1$
1(
#550
b10 &
0,
b1 +
b1 )
b1 *
1"
1%
#600
0"
0%
#650
0,
b1 +
b11 &
b10 )
1"
1%
#700
b0 &
1,
b0 +
0"
0%
0$
0(
#750
b0 )
b0 *
1"
1%
#800
b1 &
b1 +
0,
0"
0%
1$
1(
#850
b10 &
0,
b1 +
b1 )
b1 *
1"
1%
#900
0"
0%
#950
0,
b1 +
b11 &
b10 )
1"
1%
#1000
0"
0%
#1050
0,
b1 +
b100 &
b11 )
1"
1%
#1100
0"
0%
#1150
0,
b11 +
b101 &
b100 )
1"
1%
#1200
0"
0%
#1250
b0 &
1-
1!
1,
b11 +
b101 )
b11 *
1"
1%
#1300
0"
0%
#1350
1-
1!
b11 +
b0 )
1"
1%
